yayes/__init__.py
yayes-1.0.6.dist-info/DESCRIPTION.rst
yayes-1.0.6.dist-info/METADATA
yayes-1.0.6.dist-info/RECORD
yayes-1.0.6.dist-info/WHEEL
yayes-1.0.6.dist-info/metadata.json
yayes-1.0.6.dist-info/top_level.txt
yayes-1.0.6.dist-info/zip-safe
